estrade/__init__.py
estrade/enums/__init__.py
estrade/epic.py
estrade/event_manager.py
estrade/exceptions.py
estrade/graph/__init__.py
estrade/graph/base_indicator.py
estrade/graph/frame_set.py
estrade/graph/indicators/__init__.py
estrade/graph/indicators/candle_set.py
estrade/graph/indicators/pivot.py
estrade/graph/indicators/rsi.py
estrade/graph/indicators/simple_moving_average.py
estrade/mixins/__init__.py
estrade/mixins/meta.py
estrade/mixins/ref.py
estrade/mixins/timed.py
estrade/mixins/timeframe.py
estrade/mixins/transaction.py
estrade/reporting/__init__.py
estrade/reporting/csv.py
estrade/strategy.py
estrade/tick.py
estrade/tick_provider.py
estrade/trade.py
estrade/trade_provider.py
estrade-0.2.0.dist-info/WHEEL
estrade-0.2.0.dist-info/METADATA
estrade-0.2.0.dist-info/RECORD
