Metadata-Version: 2.1
Name: estrade
Version: 0.2.0
Summary: Build, Backtest and Go Live your own trading bots
Home-page: https://pypi.org/project/estrade/
License: GPL-3.0-or-later
Keywords: trading,trading-bot,backtesting-trading-strategies,backtesting
Author: Gabriel Oger
Requires-Python: >=3.6,<4.0
Classifier: Development Status :: 2 - Pre-Alpha
Classifier: Intended Audience :: Developers
Classifier: Intended Audience :: Financial and Insurance Industry
Classifier: License :: OSI Approved :: GNU General Public License v3 or later (GPLv3+)
Classifier: Natural Language :: English
Classifier: Operating System :: OS Independent
Classifier: Programming Language :: Python
Classifier: Programming Language :: Python :: 3
Classifier: Programming Language :: Python :: 3.6
Classifier: Programming Language :: Python :: 3.7
Classifier: Programming Language :: Python :: 3.8
Classifier: Topic :: Office/Business :: Financial
Classifier: Topic :: Software Development
Requires-Dist: arrow (>=0.17,<0.18)
Requires-Dist: objgraph (>=3.5.0,<4.0.0)
Requires-Dist: python-dateutil (>=2.8.1,<3.0.0)
Requires-Dist: pytz (>=2020.4,<2021.0)
Project-URL: Documentation, https://estrade.readthedocs.io/
Project-URL: Repository, https://github.com/cimourdain/estrade
